CHANGES.txt
DEVELOP.txt
LICENSE.txt
README.txt
setup.py
src/zc/__init__.py
src/zc.async.egg-info/PKG-INFO
src/zc.async.egg-info/SOURCES.txt
src/zc.async.egg-info/dependency_links.txt
src/zc.async.egg-info/namespace_packages.txt
src/zc.async.egg-info/not-zip-safe
src/zc.async.egg-info/requires.txt
src/zc.async.egg-info/top_level.txt
src/zc/async/CHANGES.txt
src/zc/async/QUICKSTART_1_VIRTUALENV.txt
src/zc/async/QUICKSTART_2_GROK.txt
src/zc/async/README.txt
src/zc/async/README_1.txt
src/zc/async/README_2.txt
src/zc/async/README_3.txt
src/zc/async/README_3a.txt
src/zc/async/README_3b.txt
src/zc/async/TODO.txt
src/zc/async/__init__.py
src/zc/async/adapters.py
src/zc/async/agent.py
src/zc/async/agent.txt
src/zc/async/basic_dispatcher_policy.zcml
src/zc/async/catastrophes.txt
src/zc/async/catastrophes_revisited.txt
src/zc/async/configure.py
src/zc/async/configure.zcml
src/zc/async/dispatcher.py
src/zc/async/dispatcher.txt
src/zc/async/dispatcher.zcml
src/zc/async/ftesting.py
src/zc/async/ftesting.txt
src/zc/async/i18n.py
src/zc/async/instanceuuid.py
src/zc/async/interfaces.py
src/zc/async/job.py
src/zc/async/job.txt
src/zc/async/jobs_and_transactions.txt
src/zc/async/legacy.py
src/zc/async/monitor.py
src/zc/async/monitor.txt
src/zc/async/monitordb.py
src/zc/async/monitordb.txt
src/zc/async/monitortests.py
src/zc/async/multidb_dispatcher_policy.zcml
src/zc/async/parallel_serial.txt
src/zc/async/partial.py
src/zc/async/queue.py
src/zc/async/queue.txt
src/zc/async/subscribers.py
src/zc/async/subscribers.txt
src/zc/async/testing.py
src/zc/async/testing.txt
src/zc/async/tests.py
src/zc/async/threadlocal.py
src/zc/async/tips.txt
src/zc/async/twisted.txt
src/zc/async/utils.py
src/zc/async/z3.py
src/zc/async/z3.txt
src/zc/async/z3tests.py
src/zc/async/examples/pi1.py
src/zc/async/examples/pi2.py
src/zc/async/examples/pi3.py