Metadata-Version: 1.0
Name: zc.async
Version: 1.5.4
Summary: Schedule durable tasks across multiple processes and machines.
Home-page: http://packages.python.org/zc.async
Author: Gary Poster
Author-email: gary.poster@canonical.com
License: ZPL
Platform: UNKNOWN
Classifier: Development Status :: 5 - Production/Stable
Classifier: Intended Audience :: Developers
Classifier: License :: OSI Approved :: Zope Public License
Classifier: Operating System :: OS Independent
Classifier: Programming Language :: Python
Classifier: Framework :: ZODB
